fabrictestbed_cli/__init__.py
fabrictestbed_cli/cli.py
fabrictestbed_cli/exceptions.py
fabrictestbed_cli/t.py
fabrictestbed_cli/api/__init__.py
fabrictestbed_cli/api/api_client.py
fabrictestbed_cli/user/__init__.py
test/__init__.py
test/test_cli.py
fabrictestbed_cli-0.15.dist-info/LICENSE
fabrictestbed_cli-0.15.dist-info/METADATA
fabrictestbed_cli-0.15.dist-info/WHEEL
fabrictestbed_cli-0.15.dist-info/entry_points.txt
fabrictestbed_cli-0.15.dist-info/top_level.txt
fabrictestbed_cli-0.15.dist-info/RECORD
