Metadata-Version: 2.1
Name: fabrictestbed-cli
Version: 0.15
Summary: FABRIC Python Client Library with CLI
Home-page: https://github.com/fabric-testbed/fabric-cli
Author: Erica Fu, Komal Thareja
Author-email: ericafu@renci.org, kthare10@unc.edu
License: UNKNOWN
Platform: UNKNOWN
Classifier: Programming Language :: Python :: 3
Classifier: License :: OSI Approved :: MIT License
Classifier: Operating System :: OS Independent
Requires-Python: >=3.7
Requires-Dist: click
Requires-Dist: pytest
Requires-Dist: fabric-credmgr-client (==0.1.4)
Requires-Dist: fabric-orchestrator-client (==0.1.0)
